README.md
setup.py
mtschem/__init__.py
mtschem/core.py
mtschem/get_from_github.py
mtschem/tests.py
mtschem.egg-info/PKG-INFO
mtschem.egg-info/SOURCES.txt
mtschem.egg-info/dependency_links.txt
mtschem.egg-info/requires.txt
mtschem.egg-info/top_level.txt